cool_graph/__init__.py
cool_graph/runners.py
cool_graph/cli/__init__.py
cool_graph/cli/config.py
cool_graph/cli/run.py
cool_graph/config/full.yaml
cool_graph/config/in_memory_data.yaml
cool_graph/config/in_memory_data2.yaml
cool_graph/config/data/default.yaml
cool_graph/config/logging/default.yaml
cool_graph/config/logging/in_memory_data.yaml
cool_graph/config/metrics/default.yaml
cool_graph/config/metrics/in_memory_data.yaml
cool_graph/config/model_params/graphconv.yaml
cool_graph/config/model_params/graphconv_optuna.yaml
cool_graph/config/model_params/nnconv.yaml
cool_graph/config/training/default.yaml
cool_graph/config/training/in_memory_data.yaml
cool_graph/data/__init__.py
cool_graph/data/batch.py
cool_graph/data/data_processor.py
cool_graph/data/dataset.py
cool_graph/data/loaders.py
cool_graph/data/utils.py
cool_graph/datasets/__init__.py
cool_graph/datasets/antifraud.py
cool_graph/datasets/multitarget.py
cool_graph/datasets/nonhomophilous.py
cool_graph/datasets/ogbn_proteins.py
cool_graph/datasets/s_ffsd.py
cool_graph/logging/__init__.py
cool_graph/logging/mlflow_logging.py
cool_graph/models/__init__.py
cool_graph/models/categorical_embeddings.py
cool_graph/models/graphconv_gnn.py
cool_graph/models/nnconv_gnn.py
cool_graph/parameter_search/__init__.py
cool_graph/parameter_search/example_objective.py
cool_graph/train/__init__.py
cool_graph/train/helpers.py
cool_graph/train/loss.py
cool_graph/train/metrics.py
cool_graph/train/plot.py
cool_graph/train/trainer.py
cool_graph-0.0.3.dist-info/LICENSE.md
cool_graph-0.0.3.dist-info/METADATA
cool_graph-0.0.3.dist-info/WHEEL
cool_graph-0.0.3.dist-info/entry_points.txt
cool_graph-0.0.3.dist-info/top_level.txt
cool_graph-0.0.3.dist-info/RECORD
